tools/__init__.py
tools/infer.py
zjw-0.0.5.dist-info/LICENSE
zjw-0.0.5.dist-info/METADATA
zjw-0.0.5.dist-info/WHEEL
zjw-0.0.5.dist-info/top_level.txt
zjw-0.0.5.dist-info/RECORD
